[
  {
    "id":"127720327755451391"
   ,"Identification":{
      "Name":"Drawer"
    }
  }
 ,{
    "id":"127723243880451395"
   ,"Identification":{
      "Name":"Marquee"
    }
  }
 ,{
    "id":"127727297314451398"
   ,"Identification":{
      "Name":"Modal Dialog"
    }
  }
 ,{
    "id":"127728748725451399"
   ,"Identification":{
      "Name":"Login"
    }
  }
 ,{
    "id":"127731345937451402"
   ,"Identification":{
      "Name":"Wizard Modal Dialog"
    }
  }
 ,{
    "id":"127732811418451403"
   ,"Identification":{
      "Name":"Left Side Column"
    }
  }
 ,{
    "id":"127736532937451406"
   ,"Identification":{
      "Name":"Right Side Column"
    }
  }
 ,{
    "id":"127740210529451409"
   ,"Identification":{
      "Name":"Left and Right Side Columns"
    }
  }
 ,{
    "id":"127744225231451412"
   ,"Identification":{
      "Name":"Minimal (No Navigation)"
    }
  }
 ,{
    "id":"127747637098451415"
   ,"Identification":{
      "Name":"Standard"
    }
  }
]
